<configuracionCliente>
	<debugLevel>DEBUG</debugLevel>
	<escenario>
		<niveles>
			<nivel1>
				<fondo>sprites/Nivel1-fondo1-XL.png</fondo>
				<fondo>sprites/Nivel1-fondo2-XL.png</fondo>
				<fondo>sprites/Nivel1-fondo3-XL.png</fondo>
			</nivel1>
			<nivel2>
				<fondo>sprites/Nivel2-fondo1.png</fondo>
				<fondo>sprites/Nivel2-fondo2.png</fondo>
				<fondo>sprites/Nivel2-fondo3.png</fondo>
			</nivel2>
		</niveles>
	</escenario>
	<sprites>
		<sprite>sprites/SpriteCodyCompleto1-230x280.png</sprite>
		<sprite>sprites/SpriteCodyCompleto2-230x280.png</sprite>
		<sprite>sprites/SpriteCodyCompleto3-230x280.png</sprite>
		<sprite>sprites/SpriteCodyCompleto4-230x280.png</sprite>
		<sprite>sprites/objetos_varios_con_ruptura.png</sprite>
		<sprite>sprites/DugCompleto-220x264.png</sprite>
		<sprite>sprites/AndoreCompleto-220x264.png</sprite>
		<sprite>sprites/HaggarCompleto-220x264.png</sprite>
		<sprite>sprites/SpriteCodyInactivo-230x280.png</sprite>
		<sprite>sprites/barraEnergia-200x600.png</sprite>
		<sprite>sprites/caraCody-95x95.png</sprite>
		<sprite>sprites/SpriteCodyCompleto1-cuchillo-230x280.png</sprite>
		<sprite>sprites/SpriteCodyCompleto2-cuchillo-230x280.png</sprite>
		<sprite>sprites/SpriteCodyCompleto3-cuchillo-230x280.png</sprite>
		<sprite>sprites/SpriteCodyCompleto4-cuchillo-230x280.png</sprite>
		<sprite>sprites/SpriteCodyCompleto1-canio-230x280.png</sprite>
		<sprite>sprites/SpriteCodyCompleto2-canio-230x280.png</sprite>
		<sprite>sprites/SpriteCodyCompleto3-canio-230x280.png</sprite>
		<sprite>sprites/SpriteCodyCompleto4-canio-230x280.png</sprite>
		<sprite>sprites/SpriteFinalBossDamnd-325x280.png</sprite>
	</sprites>
	<sonidos>
		<sonido>musica/Nivel1-musica.mp3</sonido>
		<sonido>musica/Nivel2-musica.mp3</sonido>
		<sonido>musica/acciones/golpeMano.wav</sonido>
		<sonido>musica/acciones/golpeCanio.wav</sonido>
		<sonido>musica/acciones/golpeCuchillo.wav</sonido>
		<sonido>musica/acciones/agarrarElemento.wav</sonido>
		<sonido>musica/acciones/muerteJugador.wav</sonido>
		<sonido>musica/acciones/muerteEnemigo.wav</sonido>
		<sonido>musica/acciones/recibirGolpe.wav</sonido>
	</sonidos>
</configuracionCliente>
